music2latent/__init__.py
music2latent/audio.py
music2latent/hparams.py
music2latent/hparams_inference.py
music2latent/inference.py
music2latent/models.py
music2latent/utils.py
music2latent-0.1.8.dist-info/LICENSE
music2latent-0.1.8.dist-info/METADATA
music2latent-0.1.8.dist-info/WHEEL
music2latent-0.1.8.dist-info/top_level.txt
music2latent-0.1.8.dist-info/RECORD
