Metadata-Version: 2.1
Name: music2latent
Version: 0.1.8
Summary: Encode and decode audio samples to/from compressed representations!
Home-page: https://github.com/SonyCSLParis/music2latent
Author: Sony Computer Science Laboratories Paris
Author-email: music@csl.sony.fr
License: CC BY-NC 4.0
Keywords: audio speech music compression generative-model autoencoder diffusion consistency
License-File: LICENSE
Requires-Dist: numpy
Requires-Dist: soundfile
Requires-Dist: huggingface-hub
Requires-Dist: torch
